fau/__init__.py
fau/array_set.py
fau/f32.py
fau/fixed_length_array.py
fau/integer_array.py
fau/s16.py
fau/s32.py
fau/s8.py
fau/signed_integer_array.py
fau/u16.py
fau/u32.py
fau/u8.py
fau/unsigned_integer_array.py
fau/write.py
tests/__init__.py
tests/test_array_set.py
tests/test_f32.py
tests/test_s16.py
tests/test_s32.py
tests/test_s8.py
tests/test_u16.py
tests/test_u32.py
tests/test_u8.py
fau-0.0.13.dist-info/METADATA
fau-0.0.13.dist-info/WHEEL
fau-0.0.13.dist-info/top_level.txt
fau-0.0.13.dist-info/RECORD
