Metadata-Version: 2.1
Name: fau
Version: 0.0.13
Summary: Tools for reading and writing to and from Fau byte streams.
Home-page: https://github.com/jameswilddev/fau
Author: jameswilddev
Author-email: jameswilddev@outlook.com
License: UNKNOWN
Platform: UNKNOWN
Classifier: Programming Language :: Python :: 3
Classifier: License :: OSI Approved :: MIT License
Classifier: Operating System :: OS Independent
Requires-Python: >=3.6
